rocket/__init__.py
rocket/rocket.py
rocket/tracks.py
rocket/connectors/__init__.py
rocket/connectors/base.py
rocket/connectors/files.py
rocket/connectors/project.py
rocket/connectors/socket.py
rocket/controllers/__init__.py
rocket/controllers/base.py
rocket/controllers/time.py
pyrocket-0.2.9.dist-info/LICENSE.txt
pyrocket-0.2.9.dist-info/METADATA
pyrocket-0.2.9.dist-info/WHEEL
pyrocket-0.2.9.dist-info/top_level.txt
pyrocket-0.2.9.dist-info/RECORD
