Metadata-Version: 2.1
Name: pyrocket
Version: 0.2.9
Summary: Rocket sync-tracker client
Home-page: https://github.com/Contraz/pyrocket
Author: Einar Forselv
Author-email: eforselv@gmail.com
Maintainer: Einar Forselv
Maintainer-email: eforselv@gmail.com
License: UNKNOWN
Keywords: synchronizing,music,rocket
Platform: UNKNOWN
Classifier: Programming Language :: Python
Classifier: Intended Audience :: Developers
Classifier: Topic :: Multimedia :: Graphics
Classifier: License :: OSI Approved :: zlib/libpng License
Classifier: Programming Language :: Python :: 3
Classifier: Programming Language :: Python :: 3.6
Classifier: Topic :: Software Development :: Libraries :: Application Frameworks
